nebulaX/__init__.py
nebulaX/experiment.py
nebulaX/experiment_integrations.py
nebulaX/storage.py
nebulaX/utils.py
nebulaX/visualization.py
nebulax-0.1.0.dist-info/licenses/LICENSE
nebulax-0.1.0.dist-info/METADATA
nebulax-0.1.0.dist-info/WHEEL
nebulax-0.1.0.dist-info/top_level.txt
nebulax-0.1.0.dist-info/RECORD
