Metadata-Version: 2.4
Name: nebulaX
Version: 0.1.0
Summary: A lightweight library to track and organize AI experiments.
Author-email: Vedant Kulkarni <vedantkulkarni208@gmail.com>
License-Expression: MIT
Keywords: AI,Machine Learning,Experiment Tracking,Visualization
Classifier: Development Status :: 3 - Alpha
Classifier: Intended Audience :: Developers
Classifier: Programming Language :: Python :: 3
Classifier: Programming Language :: Python :: 3.7
Classifier: Programming Language :: Python :: 3.8
Classifier: Programming Language :: Python :: 3.9
Classifier: Programming Language :: Python :: 3.10
Classifier: Topic :: Software Development :: Libraries :: Python Modules
Classifier: Topic :: Scientific/Engineering :: Artificial Intelligence
Requires-Python: >=3.7
License-File: LICENSE
Requires-Dist: matplotlib>=3.1
Requires-Dist: pandas>=1.0
Requires-Dist: tensorflow>=2.5
Requires-Dist: torch>=1.9
Requires-Dist: scikit-learn>=0.24
Dynamic: license-file
